README.rst
setup.py
madaf/__init__.py
madaf.egg-info/PKG-INFO
madaf.egg-info/SOURCES.txt
madaf.egg-info/dependency_links.txt
madaf.egg-info/requires.txt
madaf.egg-info/top_level.txt