Metadata-Version: 2.1
Name: madaf
Version: 0.0.1
Summary: Super fast key-value database similar to shelve
Home-page: https://www.github.com/etz4ai/madaf
Author: JJ Ben-Joseph
Author-email: etz@memoriesofzion.com
License: Apache
Keywords: database
Platform: UNKNOWN
Classifier: Development Status :: 1 - Planning
Classifier: Intended Audience :: Developers
Classifier: License :: OSI Approved :: Apache Software License
Requires-Python: >=3.6
